tspice/__init__.py
tspice/internal_dynamics.py
tspice/kernels.py
tspice/tidal_signal.py
tspice/utils.py
tspice/data/spice_kernels.json
tspice/integration_tools/__init__.py
tspice/integration_tools/differential_equations.py
tspice/integration_tools/initial_conditions.py
tspice-0.0.1.dist-info/licenses/LICENSE
tspice-0.0.1.dist-info/METADATA
tspice-0.0.1.dist-info/WHEEL
tspice-0.0.1.dist-info/top_level.txt
tspice-0.0.1.dist-info/RECORD
