Metadata-Version: 2.4
Name: tspice
Version: 0.0.1
Summary: Tidal signal with Python and SPICE
Home-page: https://github.com/DeivyMercado/TSPICE
Author: Deivy Mercado
Author-email: Deivy Mercado <david231097@gmail.com>
License-Expression: MIT
Project-URL: Homepage, https://github.com/DeivyMercado/TSPICE
Keywords: astrodynamics,geophysics,tides,spice
Classifier: Programming Language :: Python :: 3
Classifier: Operating System :: OS Independent
Requires-Python: >=3.7
License-File: LICENSE
Requires-Dist: numpy
Requires-Dist: scipy
Requires-Dist: spiceypy
Dynamic: author
Dynamic: home-page
Dynamic: license-file
